drf_io_serializers
