Metadata-Version: 1.1
Name: drf-io-serializers
Version: 1.0.9
Summary: Generic views, viewsets and mixins that extend the Django REST Framework ones adding separated serializers for read and write operations
Home-page: https://github.com/vintasoftware/drf-io-serializers
Author: vintasoftware
Author-email: contact@vinta.com.br
License: MIT
Keywords: Django REST Framework,Serializers,REST,API,Django
Platform: UNKNOWN
Classifier: Framework :: Django
Classifier: Framework :: Django :: 1.11
Classifier: Framework :: Django :: 2.0
Classifier: Framework :: Django :: 2.1
Classifier: Framework :: Django :: 2.2
Classifier: Framework :: Django :: 3.0
Classifier: Framework :: Django :: 3.1
Classifier: Framework :: Django :: 3.2
Classifier: Framework :: Django :: 4.0
Classifier: Intended Audience :: Developers
Classifier: License :: OSI Approved :: MIT License
Classifier: Natural Language :: English
Classifier: Programming Language :: Python :: 3
Classifier: Programming Language :: Python :: 3.7
Classifier: Programming Language :: Python :: 3.10
Classifier: Programming Language :: Python :: 3.11
